README.rst
setup.py
nameko_nova_compat/__init__.py
nameko_nova_compat/channelhandler.py
nameko_nova_compat/common.py
nameko_nova_compat/context.py
nameko_nova_compat/decorators.py
nameko_nova_compat/extensions.py
nameko_nova_compat/kombu_helpers.py
nameko_nova_compat/nova.py
nameko_nova_compat/proxy.py
nameko_nova_compat/responses.py
nameko_nova_compat/testing.py
nameko_nova_compat.egg-info/PKG-INFO
nameko_nova_compat.egg-info/SOURCES.txt
nameko_nova_compat.egg-info/dependency_links.txt
nameko_nova_compat.egg-info/requires.txt
nameko_nova_compat.egg-info/top_level.txt
nameko_nova_compat.egg-info/zip-safe
test/test_channelhandler.py
test/test_context.py
test/test_decorators.py
test/test_dependencies.py
test/test_kombu_helpers.py
test/test_nova.py
test/test_proxy.py
test/test_responses.py