Metadata-Version: 1.1
Name: nameko-nova-compat
Version: 0.0.2
Summary: Nova-RPC compatibility for nameko services
Home-page: http://github.com/onefinestay/nameko-nova-compat
Author: onefinestay
Author-email: engineering@onefinestay.com
License: Apache License, Version 2.0
Platform: UNKNOWN
Classifier: Programming Language :: Python
Classifier: Operating System :: MacOS :: MacOS X
Classifier: Operating System :: POSIX
Classifier: Programming Language :: Python :: 2.7
Classifier: Topic :: Internet
Classifier: Topic :: Software Development :: Libraries :: Python Modules
Classifier: Intended Audience :: Developers
